openassetio_traitgen/__init__.py
openassetio_traitgen/__main__.py
openassetio_traitgen/datamodel.py
openassetio_traitgen/parser.py
openassetio_traitgen/schema.json
openassetio_traitgen/generators/__init__.py
openassetio_traitgen/generators/cpp.py
openassetio_traitgen/generators/cpp_keywords.py
openassetio_traitgen/generators/helpers.py
openassetio_traitgen/generators/python.py
openassetio_traitgen/templates/cpp/package.hpp.in
openassetio_traitgen/templates/cpp/specification.hpp.in
openassetio_traitgen/templates/cpp/specifications.hpp.in
openassetio_traitgen/templates/cpp/trait.hpp.in
openassetio_traitgen/templates/cpp/traits.hpp.in
openassetio_traitgen/templates/python/__init__.py.in
openassetio_traitgen/templates/python/specifications.py.in
openassetio_traitgen/templates/python/traits.py.in
openassetio_traitgen-1.0.0a13.dist-info/licenses/LICENSE
openassetio_traitgen-1.0.0a13.dist-info/METADATA
openassetio_traitgen-1.0.0a13.dist-info/WHEEL
openassetio_traitgen-1.0.0a13.dist-info/entry_points.txt
openassetio_traitgen-1.0.0a13.dist-info/top_level.txt
openassetio_traitgen-1.0.0a13.dist-info/RECORD
